qython/__init__.py
qython/custom_grammar.txt
qython/translate.py
gabiteodoru_qython-0.1.1.dist-info/METADATA
gabiteodoru_qython-0.1.1.dist-info/WHEEL
gabiteodoru_qython-0.1.1.dist-info/top_level.txt
gabiteodoru_qython-0.1.1.dist-info/RECORD
